duowen_agent/__init__.py
duowen_agent/agents/__init__.py
duowen_agent/agents/base.py
duowen_agent/agents/component/__init__.py
duowen_agent/agents/component/base.py
duowen_agent/agents/component/chunk_extend.py
duowen_agent/agents/component/classifiers.py
duowen_agent/agents/component/code_repair.py
duowen_agent/agents/component/fuck_cosmic.py
duowen_agent/agents/component/general.py
duowen_agent/agents/component/graph_extract.py
duowen_agent/agents/component/graph_extract_v2.py
duowen_agent/agents/component/image_elements.yaml
duowen_agent/agents/component/image_interpretation.py
duowen_agent/agents/component/keywords_extract.py
duowen_agent/agents/component/merge_contexts.py
duowen_agent/agents/component/plotly_visualization.py
duowen_agent/agents/component/prompt_enhancer.py
duowen_agent/agents/component/query_rewrite.py
duowen_agent/agents/component/rank_gpt.py
duowen_agent/agents/component/reporter.py
duowen_agent/agents/component/seo_summary.py
duowen_agent/agents/component/summarization.py
duowen_agent/agents/component/text_corrector.py
duowen_agent/agents/component/text_corrector_v2.py
duowen_agent/agents/component/tool_wrapper.py
duowen_agent/agents/deepsearch.py
duowen_agent/agents/memories/__init__.py
duowen_agent/agents/memories/base.py
duowen_agent/agents/memories/conversation.py
duowen_agent/agents/react.py
duowen_agent/agents/state.py
duowen_agent/deep_research/__init__.py
duowen_agent/deep_research/agents/__init__.py
duowen_agent/deep_research/agents/agents.py
duowen_agent/deep_research/builder.py
duowen_agent/deep_research/config/__init__.py
duowen_agent/deep_research/config/agents.py
duowen_agent/deep_research/config/configuration.py
duowen_agent/deep_research/config/loader.py
duowen_agent/deep_research/config/questions.py
duowen_agent/deep_research/config/report_style.py
duowen_agent/deep_research/config/tools.py
duowen_agent/deep_research/coordinator.py
duowen_agent/deep_research/nodes.py
duowen_agent/deep_research/prompts/__init__.py
duowen_agent-0.1.104.dist-info/METADATA
duowen_agent-0.1.104.dist-info/WHEEL
duowen_agent-0.1.104.dist-info/RECORD
