Metadata-Version: 2.3
Name: duowen-agent
Version: 0.1.104
Summary: 多闻LLM核心工具包
Author: liurui
Author-email: liurui@asiainfo.com
Requires-Python: >=3.11,<3.13
Classifier: Programming Language :: Python :: 3
Classifier: Programming Language :: Python :: 3.11
Classifier: Programming Language :: Python :: 3.12
Requires-Dist: PyYAML (>=5.3)
Requires-Dist: anyio (>=4.9.0)
Requires-Dist: chardet (>=5.2.0)
Requires-Dist: datrie (>=0.8.3,<0.9.0)
Requires-Dist: deepagents (>=0.3.0)
Requires-Dist: future (>=1.0.0)
Requires-Dist: graspologic (==3.4.4)
Requires-Dist: hanziconv (>=0.3.2,<0.4.0)
Requires-Dist: html2text (>=2024.2.26)
Requires-Dist: httpx-sse (>=0.4.0)
Requires-Dist: httpx[socks] (>=0.28.1,<0.29.0)
Requires-Dist: jieba (>=0.42.1)
Requires-Dist: jinja2 (>=3.1.6)
Requires-Dist: json-repair (>=0.50.0)
Requires-Dist: json5 (>=0.9.0)
Requires-Dist: jsonlines (>=4.0.0)
Requires-Dist: langchain-core (>=1.2.5)
Requires-Dist: langchain[openai] (>=1.1.3)
Requires-Dist: langgraph (>=0.6.3)
Requires-Dist: lxml (>=5.4.0)
Requires-Dist: mammoth (>=1.11.0)
Requires-Dist: markdownify (>=0.14.1)
Requires-Dist: matplotlib (>=3.9.2)
Requires-Dist: mcp (>=1.23.0)
Requires-Dist: mistune (>=3.1.3)
Requires-Dist: networkx (>=3.5)
Requires-Dist: nltk (>=3.9.1,<4.0.0)
Requires-Dist: numpy (>=1.0)
Requires-Dist: openai (>=1.10.0)
Requires-Dist: openpyxl (>=3.1.2)
Requires-Dist: pandas (>=2.2.1)
Requires-Dist: plotly (>=6.1.2)
Requires-Dist: pydantic (>=2.7.0)
Requires-Dist: pydantic-extra-types (>=2.10.5)
Requires-Dist: pymupdf4llm (>=0.0.17)
Requires-Dist: python-dotenv (>=0.21.0)
Requires-Dist: python-pptx (>=1.0.2)
Requires-Dist: pyvis (>=0.3.2)
Requires-Dist: requests (>=2.32.4,<3)
Requires-Dist: scipy (>=1.12.0)
Requires-Dist: sqlalchemy (>=1.4,<3)
Requires-Dist: sseclient-py (>=1.8.0)
Requires-Dist: tabulate (>=0.9.0)
Requires-Dist: tavily-python (>=0.5.1)
Requires-Dist: tiktoken (>=0.7,<1)
Requires-Dist: trafilatura (>=2.0.0)
Requires-Dist: uv (>=0.9.6)
Requires-Dist: xlrd (>=2.0.1)
Requires-Dist: xmltodict (>=0.14.2)
